flux_sdk/.DS_Store
flux_sdk/__init__.py
flux_sdk/benefits_administration/__init__.py
flux_sdk/benefits_administration/capabilities/__init__.py
flux_sdk/benefits_administration/capabilities/process_employees_deductions/BUILD
flux_sdk/benefits_administration/capabilities/process_employees_deductions/__init__.py
flux_sdk/benefits_administration/capabilities/process_employees_deductions/data_models.py
flux_sdk/benefits_administration/capabilities/process_employees_deductions/interface.py
flux_sdk/benefits_administration/capabilities/report_employees_hr_data/BUILD
flux_sdk/benefits_administration/capabilities/report_employees_hr_data/__init__.py
flux_sdk/benefits_administration/capabilities/report_employees_hr_data/data_models.py
flux_sdk/benefits_administration/capabilities/report_employees_hr_data/interface.py
flux_sdk/custom_object_sync/__init__.py
flux_sdk/custom_object_sync/data_models/__init__.py
flux_sdk/custom_object_sync/data_models/models.py
flux_sdk/custom_object_sync/inward_sync/__init__.py
flux_sdk/custom_object_sync/inward_sync/interface.py
flux_sdk/custom_object_sync/outward_sync/__init__.py
flux_sdk/custom_object_sync/outward_sync/interface.py
flux_sdk/employee_census/__init__.py
flux_sdk/employee_census/report_employee_census_data/__init__.py
flux_sdk/employee_census/report_employee_census_data/interface.py
flux_sdk/employee_census/upload_employee_census_data/__init__.py
flux_sdk/employee_census/upload_employee_census_data/data_models.py
flux_sdk/employee_census/upload_employee_census_data/interface.py
flux_sdk/equity/__init__.py
flux_sdk/equity/capabilities/__init__.py
flux_sdk/equity/capabilities/update_equity_grant/BUILD
flux_sdk/equity/capabilities/update_equity_grant/__init__.py
flux_sdk/equity/capabilities/update_equity_grant/data_models.py
flux_sdk/equity/capabilities/update_equity_grant/interface.py
flux_sdk/equity/capabilities/update_equity_grant/strategies.py
flux_sdk/etl/__init__.py
flux_sdk/etl/capabilities/__init__.py
rippling_flux_sdk-0.68.144.dist-info/METADATA
rippling_flux_sdk-0.68.144.dist-info/WHEEL
rippling_flux_sdk-0.68.144.dist-info/licenses/LICENSE
rippling_flux_sdk-0.68.144.dist-info/RECORD
