Metadata-Version: 2.4
Name: rippling-flux-sdk
Version: 0.68.144
Summary: Defines the interfaces and data-models used by Rippling Flux Apps.
License-File: LICENSE
Author: Rippling Apps
Author-email: apps@rippling.com
Requires-Python: >=3.10,<4.0
Classifier: Programming Language :: Python :: 3
Classifier: Programming Language :: Python :: 3.10
Classifier: Programming Language :: Python :: 3.11
Classifier: Programming Language :: Python :: 3.12
Classifier: Programming Language :: Python :: 3.13
Classifier: Programming Language :: Python :: 3.14
Requires-Dist: certifi (>=2025.4.26)
Requires-Dist: charset-normalizer (>=2.1.1)
Requires-Dist: click (>=8.0,<9)
Requires-Dist: grpcio (>=1.56.2)
Requires-Dist: idna (>=2.10)
Requires-Dist: protobuf (>=4.23.4)
Requires-Dist: pydantic-core
Requires-Dist: pydantic[email] (>=2.11.0)
Requires-Dist: pyrfc3339 (>=2.0.1)
Requires-Dist: requests (>=2.31.0)
Requires-Dist: rp-twirp (==1.1.1)
Requires-Dist: ruamel.yaml (>=0.17.10)
Requires-Dist: structlog (>=21.5.0)
Requires-Dist: urllib3 (>=1.26.18)
